genome_update/__init__.py
genome_update/__main__.py
genome_update/compare_isolates.py
genome_update/dictonary_handler.py
genome_update/downloader.py
genome_update/isolate_finder.py
genome_update/sequence_statistics.py
genome_update/yaml_handler.py
genome_update-0.1.6.8.dist-info/DESCRIPTION.rst
genome_update-0.1.6.8.dist-info/METADATA
genome_update-0.1.6.8.dist-info/RECORD
genome_update-0.1.6.8.dist-info/WHEEL
genome_update-0.1.6.8.dist-info/entry_points.txt
genome_update-0.1.6.8.dist-info/metadata.json
genome_update-0.1.6.8.dist-info/top_level.txt
