Metadata-Version: 2.0
Name: genome-update
Version: 0.1.6.8
Summary: A script for updating a local directory with genomes, from NCBI assembly files
Home-page: https://github.com/Emisam/genome_update.git
Author: Emil Samuelsson
Author-email: Emil@Samuelsson.pp.se
License: MIT
Platform: UNKNOWN
Classifier: Development Status :: 3 - Alpha
Classifier: Intended Audience :: Science/Research
Classifier: Topic :: Scientific/Engineering :: Bio-Informatics
Classifier: License :: OSI Approved :: MIT License
Classifier: Programming Language :: Python
Requires-Dist: PyYAML
Requires-Dist: pandas
